{
  "name": "CORE - Get Audit Trail",
  "description": "",
  "version": 3,
  "private": true,
  "concurrency": 1,
  "code": {
    "number": 0,
    "provider": "workato_api_platform",
    "name": "receive_request",
    "as": "67c0f137",
    "keyword": "trigger",
    "dynamicPickListSelection": {
      "response.responses.0.http_status_code": "200 - OK"
    },
    "toggleCfg": {
      "response.responses.0.http_status_code": true
    },
    "input": {
      "request": {
        "content_type": "json",
        "path_params": "[{\"name\":\"case_id\",\"type\":\"string\",\"optional\":false,\"label\":\"case id\",\"control_type\":\"text\"}]"
      },
      "response": {
        "content_type": "json",
        "responses": [
          {
            "http_status_code": "200",
            "name": "200 - OK",
            "body_schema": "[{\"label\":\"Events\",\"of\":\"object\",\"properties\":[{\"control_type\":\"text\",\"label\":\"Event ID\",\"type\":\"string\",\"name\":\"eventId\"},{\"control_type\":\"text\",\"label\":\"Case ID\",\"type\":\"string\",\"name\":\"caseId\"},{\"control_type\":\"text\",\"label\":\"Event type\",\"type\":\"string\",\"name\":\"eventType\"},{\"control_type\":\"text\",\"label\":\"User email\",\"type\":\"string\",\"name\":\"userEmail\"},{\"control_type\":\"text\",\"label\":\"Timestamp\",\"type\":\"string\",\"name\":\"timestamp\"},{\"control_type\":\"text\",\"label\":\"Details\",\"type\":\"string\",\"name\":\"details\"},{\"control_type\":\"text\",\"label\":\"Old value\",\"type\":\"string\",\"name\":\"oldValue\"},{\"control_type\":\"text\",\"label\":\"New value\",\"type\":\"string\",\"name\":\"newValue\"}],\"type\":\"array\",\"name\":\"events\"}]"
          }
        ]
      }
    },
    "extended_output_schema": [
      {
        "label": "Context",
        "name": "context",
        "properties": [
          {
            "control_type": "text",
            "label": "Calling IP address",
            "optional": true,
            "type": "string",
            "name": "calling_ip"
          },
          {
            "properties": [
              {
                "control_type": "integer",
                "label": "Access profile ID",
                "parse_output": "integer_conversion",
                "optional": true,
                "type": "integer",
                "name": "id"
              },
              {
                "control_type": "text",
                "label": "Access profile name",
                "optional": true,
                "type": "string",
                "name": "name"
              },
              {
                "control_type": "text",
                "label": "Access profile authentication type",
                "optional": true,
                "type": "string",
                "name": "type"
              }
            ],
            "label": "Access profile",
            "type": "object",
            "name": "access_profile"
          },
          {
            "properties": [
              {
                "control_type": "text",
                "label": "API client ID",
                "optional": true,
                "type": "string",
                "name": "id"
              },
              {
                "control_type": "text",
                "label": "API client name",
                "optional": true,
                "type": "string",
                "name": "name"
              }
            ],
            "label": "API client",
            "type": "object",
            "name": "client"
          },
          {
            "properties": [
              {
                "control_type": "integer",
                "label": "Issued At",
                "render_input": "date_time_conversion",
                "parse_output": "date_time_conversion",
                "optional": true,
                "type": "date_time",
                "name": "iat"
              },
              {
                "control_type": "integer",
                "label": "Not Before",
                "render_input": "date_time_conversion",
                "parse_output": "date_time_conversion",
                "optional": true,
                "type": "date_time",
                "name": "nbf"
              },
              {
                "control_type": "integer",
                "label": "Expiration Time",
                "render_input": "date_time_conversion",
                "parse_output": "date_time_conversion",
                "optional": true,
                "type": "date_time",
                "name": "exp"
              },
              {
                "control_type": "text",
                "label": "Audience",
                "optional": true,
                "type": "string",
                "name": "aud"
              },
              {
                "control_type": "text",
                "label": "JWT ID",
                "optional": true,
                "type": "string",
                "name": "jti"
              },
              {
                "control_type": "text",
                "label": "Issuer",
                "optional": true,
                "type": "string",
                "name": "iss"
              }
            ],
            "label": "JWT claims",
            "type": "object",
            "name": "jwt_payload"
          },
          {
            "properties": [
              {
                "properties": [
                  {
                    "control_type": "checkbox",
                    "label": "Active",
                    "render_input": "boolean_conversion",
                    "parse_output": "boolean_conversion",
                    "optional": true,
                    "toggle_hint": "Select from option list",
                    "toggle_field": {
                      "label": "Active",
                      "control_type": "text",
                      "toggle_hint": "Use custom value",
                      "optional": true,
                      "type": "boolean",
                      "name": "active"
                    },
                    "type": "boolean",
                    "name": "active"
                  },
                  {
                    "control_type": "text",
                    "label": "Scope",
                    "optional": true,
                    "type": "string",
                    "name": "scope"
                  },
                  {
                    "control_type": "text",
                    "label": "Client ID",
                    "optional": true,
                    "type": "string",
                    "name": "client_id"
                  },
                  {
                    "control_type": "text",
                    "label": "Username",
                    "optional": true,
                    "type": "string",
                    "name": "username"
                  },
                  {
                    "control_type": "text",
                    "label": "Token type",
                    "optional": true,
                    "type": "string",
                    "name": "token_type"
                  },
                  {
                    "control_type": "text",
                    "label": "Exp",
                    "optional": true,
                    "type": "string",
                    "name": "exp"
                  }
                ],
                "label": "Response Body",
                "type": "object",
                "name": "payload"
              }
            ],
            "label": "Token introspection",
            "type": "object",
            "name": "introspect"
          }
        ],
        "type": "object"
      },
      {
        "label": "Request path parameters",
        "name": "path_params",
        "properties": [
          {
            "control_type": "text",
            "label": "case id",
            "name": "case_id",
            "type": "string",
            "optional": false
          }
        ],
        "type": "object"
      }
    ],
    "block": [
      {
        "number": 1,
        "provider": "google_sheets",
        "name": "search_spreadsheet_rows_v4_new",
        "as": "3311c1d6",
        "keyword": "action",
        "dynamicPickListSelection": {
          "team_drives": "My Drive",
          "spreadsheet": "LBC Management System"
        },
        "input": {
          "team_drives": "my_drive",
          "spreadsheet": "1Uo2Z0jC_jlD5U3MxCH0s1W59XHBfkEaiiOGZaI39O48",
          "count": "200",
          "sheet": "Audit Events",
          "data": {
            "col_Case ID": "#{_dp('{\"pill_type\":\"output\",\"provider\":\"workato_api_platform\",\"line\":\"67c0f137\",\"path\":[\"path_params\",\"case_id\"]}')}"
          }
        },
        "extended_output_schema": [
          {
            "control_type": "text",
            "label": "Spreadsheet ID",
            "name": "spreadsheet_id",
            "type": "string"
          },
          {
            "control_type": "text",
            "label": "Spreadsheet name",
            "name": "spreadsheet_name",
            "type": "string"
          },
          {
            "control_type": "text",
            "label": "Sheet name",
            "name": "sheet",
            "type": "string"
          },
          {
            "label": "Rows",
            "name": "rows",
            "of": "object",
            "properties": [
              {
                "control_type": "number",
                "label": "Row number",
                "parse_output": "integer_conversion",
                "type": "integer",
                "name": "row_number"
              },
              {
                "control_type": "text",
                "label": "Event ID",
                "old_name": "col_Event_ID",
                "custom_attribute": 1,
                "type": "string",
                "name": "col_Event ID"
              },
              {
                "control_type": "text",
                "label": "Case ID",
                "old_name": "col_Case_ID",
                "custom_attribute": 2,
                "type": "string",
                "name": "col_Case ID"
              },
              {
                "control_type": "text",
                "label": "Event Type",
                "old_name": "col_Event_Type",
                "custom_attribute": 3,
                "type": "string",
                "name": "col_Event Type"
              },
              {
                "control_type": "text",
                "label": "User Email",
                "old_name": "col_User_Email",
                "custom_attribute": 4,
                "type": "string",
                "name": "col_User Email"
              }
            ],
            "type": "array"
          }
        ],
        "extended_input_schema": [
          {
            "control_type": "select",
            "extends_schema": true,
            "hint": "Select a sheet to search for rows. The sheet must have at least one header row. <a href='https://docs.workato.com/connectors/google-sheets/action-add-row.html#setting-up-the-google-sheet' target='_blank'>Learn more</a>",
            "label": "Sheet",
            "name": "sheet",
            "optional": false,
            "pick_list": [
              [
                "Business Cases",
                "Business Cases"
              ],
              [
                "Audit Events",
                "Audit Events"
              ],
              [
                "Reviews",
                "Reviews"
              ],
              [
                "Approvals",
                "Approvals"
              ],
              [
                "Comments",
                "Comments"
              ],
              [
                "System Config",
                "System Config"
              ],
              [
                "Version History",
                "Version History"
              ],
              [
                "Attachments",
                "Attachments"
              ]
            ],
            "toggle_field": {
              "control_type": "text",
              "label": "Sheet name",
              "toggle_hint": "Use sheet name",
              "extends_schema": true,
              "change_on_blur": true,
              "toggle_to_secondary_hint": "Use sheet name",
              "toggle_to_primary_hint": "Select a sheet",
              "hint": "Use <b>Sheet name</b> pill from the output of other Google Sheets’ triggers/actions. Or enter sheet name manually. The sheet must have at least 1 header row in input field.",
              "type": "string",
              "name": "sheet_name"
            },
            "toggle_hint": "Select a sheet",
            "type": "string"
          },
          {
            "hint": "Enter one or more search values. Workato will search for rows matching <b>ALL</b> of the search values below.",
            "label": "Columns",
            "name": "data",
            "properties": [
              {
                "control_type": "text",
                "label": "Event ID",
                "optional": true,
                "sticky": true,
                "hint": "Search for an exact match of the search value you enter here. Search value is case-sensitive and can contain space.",
                "type": "string",
                "name": "col_Event ID"
              },
              {
                "control_type": "text",
                "label": "Case ID",
                "optional": true,
                "sticky": true,
                "hint": "Search for an exact match of the search value you enter here. Search value is case-sensitive and can contain space.",
                "type": "string",
                "name": "col_Case ID"
              },
              {
                "control_type": "text",
                "label": "Event Type",
                "optional": true,
                "sticky": true,
                "hint": "Search for an exact match of the search value you enter here. Search value is case-sensitive and can contain space.",
                "type": "string",
                "name": "col_Event Type"
              },
              {
                "control_type": "text",
                "label": "User Email",
                "optional": true,
                "sticky": true,
                "hint": "Search for an exact match of the search value you enter here. Search value is case-sensitive and can contain space.",
                "type": "string",
                "name": "col_User Email"
              }
            ],
            "sticky": true,
            "type": "object"
          },
          {
            "control_type": "number",
            "default": 200,
            "hint": "Maximum number of matched rows to be returned. Minimum accepted value is <b>1</b> and maximum accepted value is <b>50000</b>.",
            "label": "Search result size",
            "name": "count",
            "optional": true,
            "parse_output": "float_conversion",
            "type": "number"
          }
        ],
        "uuid": "7e491c49-bb09-4471-9c70-707d15366c28"
      }
    ],
    "comment": "Define the request and response parameters for this API endpoint",
    "uuid": "53ca0a1b-d014-4da6-9bc0-7d12b9d5928e"
  },
  "config": [
    {
      "keyword": "application",
      "provider": "workato_api_platform",
      "skip_validation": false,
      "account_id": null
    },
    {
      "keyword": "application",
      "provider": "google_sheets",
      "skip_validation": false,
      "account_id": {
        "zip_name": "lbcm_google_sheets.connection.json",
        "name": "LBCM - Google Sheets",
        "folder": ""
      }
    }
  ]
}