{
  "name": "UTIL - Generate Case ID",
  "description": "",
  "version": 4,
  "private": true,
  "concurrency": 1,
  "code": {
    "number": 0,
    "provider": "workato_recipe_function",
    "name": "execute",
    "as": "8ee3d2df",
    "keyword": "trigger",
    "input": {
      "result_schema_json": "[{\"name\":\"case_id\",\"type\":\"string\",\"optional\":false,\"control_type\":\"text\",\"label\":\"Case ID\"}]"
    },
    "block": [
      {
        "number": 1,
        "provider": "workato_variable",
        "name": "declare_variable",
        "as": "676aee43",
        "keyword": "action",
        "input": {
          "variables": {
            "schema": "[{\"name\":\"case_id\",\"type\":\"string\",\"optional\":true,\"label\":\"case_id\",\"details\":{\"real_name\":\"case_id\"},\"control_type\":\"text\",\"parent\":[\"variables\",\"data\"]}]",
            "data": {
              "case_id": "=\"LBC-\" + now.to_i.to_s.last(8)"
            }
          }
        },
        "extended_output_schema": [
          {
            "control_type": "text",
            "label": "case_id",
            "name": "case_id",
            "optional": true,
            "type": "string",
            "details": {
              "real_name": "case_id"
            }
          }
        ],
        "extended_input_schema": [
          {
            "add_field_label": "Add a variable",
            "control_type": "form-schema-builder",
            "empty_schema_title": "Add variables by giving them a name, type and default value",
            "exclude_fields": [
              "hint"
            ],
            "item_label": "variable",
            "label": "Variables",
            "mark_as_required": true,
            "name": "variables",
            "ngIf": "!input.name",
            "optional": true,
            "properties": [
              {
                "control_type": "text",
                "label": "Schema",
                "extends_schema": true,
                "broadcast_change_event": true,
                "type": "string",
                "name": "schema"
              },
              {
                "properties": [
                  {
                    "control_type": "text",
                    "label": "case_id",
                    "name": "case_id",
                    "type": "string",
                    "optional": true,
                    "details": {
                      "real_name": "case_id"
                    },
                    "parent": [
                      "variables",
                      "data"
                    ],
                    "hint": "Defaults to nil if not supplied.",
                    "sticky": true
                  }
                ],
                "label": "Data",
                "type": "object",
                "name": "data"
              }
            ],
            "type": "object"
          }
        ],
        "visible_config_fields": [
          "variables.data.case_id"
        ],
        "uuid": "442ab8f2-e7f3-4381-ad44-6c603a54bd0e"
      },
      {
        "number": 2,
        "provider": "workato_recipe_function",
        "name": "return_result",
        "as": "fa4c0f62",
        "keyword": "action",
        "input": {
          "result": {
            "case_id": "#{_dp('{\"pill_type\":\"output\",\"provider\":\"workato_variable\",\"line\":\"676aee43\",\"path\":[\"case_id\"]}')}"
          }
        },
        "extended_output_schema": [
          {
            "label": "Result",
            "name": "result",
            "properties": [
              {
                "control_type": "text",
                "label": "Case ID",
                "name": "case_id",
                "type": "string",
                "optional": false
              }
            ],
            "type": "object"
          }
        ],
        "extended_input_schema": [
          {
            "label": "Result",
            "name": "result",
            "properties": [
              {
                "control_type": "text",
                "label": "Case ID",
                "name": "case_id",
                "type": "string",
                "optional": false
              }
            ],
            "type": "object"
          }
        ],
        "uuid": "c0c565c6-7c63-469e-97f9-03c6989878f9"
      }
    ],
    "uuid": "1142f775-f976-48a7-8f70-e6550d674470"
  },
  "config": [
    {
      "keyword": "application",
      "provider": "workato_recipe_function",
      "skip_validation": false,
      "account_id": null
    },
    {
      "keyword": "application",
      "provider": "workato_variable",
      "skip_validation": false,
      "account_id": null
    }
  ]
}