{
  "name": "Opportunity Search By Name",
  "version": 3,
  "private": true,
  "concurrency": 1,
  "code": {
    "number": 0,
    "provider": "workato_api_platform",
    "name": "receive_request",
    "as": "c2630a95",
    "keyword": "trigger",
    "dynamicPickListSelection": {
      "response.responses.0.http_status_code": "200 - OK"
    },
    "toggleCfg": {
      "response.responses.0.http_status_code": true
    },
    "input": {
      "request": {
        "content_type": "json",
        "headers": "[{\"name\":\"user_token\",\"type\":\"string\",\"optional\":false,\"label\":\"User Token\",\"control_type\":\"text\"},{\"name\":\"opportunity_name\",\"type\":\"string\",\"optional\":false,\"label\":\"Opportunity Name\",\"control_type\":\"text\"},{\"name\":\"close_date\",\"type\":\"string\",\"optional\":false,\"label\":\"Close Date\",\"control_type\":\"text\"}]"
      },
      "response": {
        "content_type": "json",
        "responses": [
          {
            "http_status_code": "200",
            "name": "ok",
            "body_schema": "[{\"control_type\":\"text\",\"label\":\"Output\",\"type\":\"string\",\"name\":\"output\"}]"
          }
        ]
      }
    },
    "extended_output_schema": [
      {
        "label": "Context",
        "name": "context",
        "properties": [
          {
            "control_type": "text",
            "label": "Calling IP address",
            "optional": true,
            "type": "string",
            "name": "calling_ip"
          },
          {
            "properties": [
              {
                "control_type": "integer",
                "label": "Access profile ID",
                "parse_output": "integer_conversion",
                "optional": true,
                "type": "integer",
                "name": "id"
              },
              {
                "control_type": "text",
                "label": "Access profile name",
                "optional": true,
                "type": "string",
                "name": "name"
              },
              {
                "control_type": "text",
                "label": "Access profile authentication type",
                "optional": true,
                "type": "string",
                "name": "type"
              }
            ],
            "label": "Access profile",
            "type": "object",
            "name": "access_profile"
          },
          {
            "properties": [
              {
                "control_type": "text",
                "label": "API client ID",
                "optional": true,
                "type": "string",
                "name": "id"
              },
              {
                "control_type": "text",
                "label": "API client name",
                "optional": true,
                "type": "string",
                "name": "name"
              }
            ],
            "label": "API client",
            "type": "object",
            "name": "client"
          },
          {
            "properties": [
              {
                "control_type": "integer",
                "label": "Issued At",
                "render_input": "date_time_conversion",
                "parse_output": "date_time_conversion",
                "optional": true,
                "type": "date_time",
                "name": "iat"
              },
              {
                "control_type": "integer",
                "label": "Not Before",
                "render_input": "date_time_conversion",
                "parse_output": "date_time_conversion",
                "optional": true,
                "type": "date_time",
                "name": "nbf"
              },
              {
                "control_type": "integer",
                "label": "Expiration Time",
                "render_input": "date_time_conversion",
                "parse_output": "date_time_conversion",
                "optional": true,
                "type": "date_time",
                "name": "exp"
              },
              {
                "control_type": "text",
                "label": "Audience",
                "optional": true,
                "type": "string",
                "name": "aud"
              },
              {
                "control_type": "text",
                "label": "JWT ID",
                "optional": true,
                "type": "string",
                "name": "jti"
              },
              {
                "control_type": "text",
                "label": "Issuer",
                "optional": true,
                "type": "string",
                "name": "iss"
              }
            ],
            "label": "JWT claims",
            "type": "object",
            "name": "jwt_payload"
          },
          {
            "properties": [
              {
                "properties": [
                  {
                    "control_type": "checkbox",
                    "label": "Active",
                    "render_input": "boolean_conversion",
                    "parse_output": "boolean_conversion",
                    "optional": true,
                    "toggle_hint": "Select from option list",
                    "toggle_field": {
                      "label": "Active",
                      "control_type": "text",
                      "toggle_hint": "Use custom value",
                      "optional": true,
                      "type": "boolean",
                      "name": "active"
                    },
                    "type": "boolean",
                    "name": "active"
                  },
                  {
                    "control_type": "text",
                    "label": "Scope",
                    "optional": true,
                    "type": "string",
                    "name": "scope"
                  },
                  {
                    "control_type": "text",
                    "label": "Client ID",
                    "optional": true,
                    "type": "string",
                    "name": "client_id"
                  },
                  {
                    "control_type": "text",
                    "label": "Username",
                    "optional": true,
                    "type": "string",
                    "name": "username"
                  },
                  {
                    "control_type": "text",
                    "label": "Token type",
                    "optional": true,
                    "type": "string",
                    "name": "token_type"
                  },
                  {
                    "control_type": "text",
                    "label": "Exp",
                    "optional": true,
                    "type": "string",
                    "name": "exp"
                  }
                ],
                "label": "Response Body",
                "type": "object",
                "name": "payload"
              }
            ],
            "label": "Token introspection",
            "type": "object",
            "name": "introspect"
          },
          {
            "properties": [
              {
                "control_type": "text",
                "label": "User Token",
                "name": "user_token",
                "type": "string",
                "optional": false
              },
              {
                "control_type": "text",
                "label": "Opportunity Name",
                "name": "opportunity_name",
                "type": "string",
                "optional": false
              },
              {
                "control_type": "text",
                "label": "Close Date",
                "name": "close_date",
                "type": "string",
                "optional": false
              }
            ],
            "label": "Request headers",
            "type": "object",
            "name": "headers"
          }
        ],
        "type": "object"
      }
    ],
    "block": [
      {
        "number": 1,
        "provider": "workato_variable",
        "name": "declare_variable",
        "as": "e232ff3e",
        "keyword": "action",
        "input": {
          "variables": {
            "schema": "[{\"control_type\":\"text\",\"label\":\"On_behalf_of_user_email\",\"name\":\"output\",\"type\":\"string\",\"optional\":true,\"details\":{\"real_name\":\"output\"},\"parent\":[\"variables\",\"data\"],\"hint\":\"Defaults to nil if not supplied.\",\"sticky\":true}]",
            "data": {
              "output": "="
            }
          }
        },
        "extended_output_schema": [
          {
            "control_type": "text",
            "hint": "Defaults to nil if not supplied.",
            "label": "On_behalf_of_user_email",
            "name": "output",
            "optional": true,
            "sticky": true,
            "type": "string",
            "details": {
              "real_name": "output"
            }
          }
        ],
        "extended_input_schema": [
          {
            "add_field_label": "Add a variable",
            "control_type": "form-schema-builder",
            "empty_schema_title": "Add variables by giving them a name, type and default value",
            "exclude_fields": [
              "hint"
            ],
            "item_label": "variable",
            "label": "Variables",
            "mark_as_required": true,
            "name": "variables",
            "ngIf": "!input.name",
            "optional": true,
            "properties": [
              {
                "control_type": "text",
                "label": "Schema",
                "extends_schema": true,
                "broadcast_change_event": true,
                "type": "string",
                "name": "schema"
              },
              {
                "properties": [
                  {
                    "control_type": "text",
                    "label": "On_behalf_of_user_email",
                    "name": "output",
                    "type": "string",
                    "optional": true,
                    "details": {
                      "real_name": "output"
                    },
                    "parent": [
                      "variables",
                      "data"
                    ],
                    "hint": "Defaults to nil if not supplied.",
                    "sticky": true
                  }
                ],
                "label": "Data",
                "type": "object",
                "name": "data"
              }
            ],
            "type": "object"
          }
        ],
        "visible_config_fields": [
          "variables.data.output"
        ],
        "uuid": "ded4dec7-b95c-4f49-b3c3-5b7f10004ed1"
      },
      {
        "number": 2,
        "keyword": "if",
        "input": {
          "type": "compound",
          "operand": "and",
          "conditions": [
            {
              "operand": "not_contains",
              "lhs": "#{_dp('{\"pill_type\":\"output\",\"provider\":\"workato_api_platform\",\"line\":\"c2630a95\",\"path\":[\"context\",\"headers\",\"user_token\"]}')}",
              "rhs": "@redhat.com",
              "uuid": "16e1ba3d-947c-4647-9a6c-2737041737a4"
            }
          ]
        },
        "block": [
          {
            "number": 3,
            "provider": "workato_variable",
            "name": "declare_variable",
            "as": "e34d7184",
            "keyword": "action",
            "input": {
              "variables": {
                "schema": "[{\"control_type\":\"text\",\"label\":\"public_key\",\"name\":\"public_key\",\"type\":\"string\",\"optional\":true,\"details\":{\"real_name\":\"public_key\"},\"parent\":[\"variables\",\"data\"],\"hint\":\"Defaults to nil if not supplied.\",\"sticky\":true}]",
                "data": {
                  "public_key": "-----BEGIN PUBLIC KEY-----\nMIICIjANBgkqhkiG9w0BAQEFAAOCAg8AMIICCgKCAgEAwKVe5MH66uvRvs7NnVNr\nhlEwd45kJmaen5Digf4PcB8IxY4a9MrXD7xuhTPPZuNX0lLNuWDvBkQNzY0DwsHv\nLW3mTAZLnQG90EWMFWziQJfSAQ60epGkSlMkd4IL9HUuZa2/tGDy9Bt5pdSfqhrb\nAA932Zg1BGCL9cY20lfc+4arqY1qUyMkMz210RG3yLWq80dXKD8ziEeRbzGv8V1H\nBJE0M15GsKxcfD/tzx95E3WTcGxJJhqnFFEEdVgB/yvMM4E2WlyI+XWmHhIe2NCm\nhofD7wdOokpuAKhgdIUlsKi79o760F123DbzWk7sprErG6p0VkJ+LZESv8/mqtlE\nXHz8zgzTkDhlUH3IJm829ouGXFSRoRDEea6We8VHJbLODSAlIeAAXylnsg9czVdn\nkXqBBnnHkeERblpccTfMysTFWYMeTykHIitnINBoTOz/7jLNf/TgvTFwHHL6TvD5\nTSq5FsID9YJ60kyucqWELEVt18VMgy3O8HA4B4kxL4hpSoO+7a2ahOROTvdDEP2Z\nyE7jsIL4mmSUrsEthM+9jFIPRjDHJD40uTbHEXhImKFPQ3nqHi8SgI4qSoZ5YE+3\nRO1ZnqtMoSP1C6TvPKo0ymH9xWXpvAmyX5afcKNXD00wcjgAgRkF0oAbSp4IuAO7\nZw6wNCKDuc5HmGgW29FSifECAwEAAQ==\n-----END PUBLIC KEY-----"
                }
              }
            },
            "extended_output_schema": [
              {
                "control_type": "text",
                "hint": "Defaults to nil if not supplied.",
                "label": "public_key",
                "name": "public_key",
                "optional": true,
                "sticky": true,
                "type": "string",
                "details": {
                  "real_name": "public_key"
                }
              }
            ],
            "extended_input_schema": [
              {
                "add_field_label": "Add a variable",
                "control_type": "form-schema-builder",
                "empty_schema_title": "Add variables by giving them a name, type and default value",
                "exclude_fields": [
                  "hint"
                ],
                "item_label": "variable",
                "label": "Variables",
                "mark_as_required": true,
                "name": "variables",
                "ngIf": "!input.name",
                "optional": true,
                "properties": [
                  {
                    "control_type": "text",
                    "label": "Schema",
                    "extends_schema": true,
                    "broadcast_change_event": true,
                    "type": "string",
                    "name": "schema"
                  },
                  {
                    "properties": [
                      {
                        "control_type": "text",
                        "label": "public_key",
                        "name": "public_key",
                        "type": "string",
                        "optional": true,
                        "details": {
                          "real_name": "public_key"
                        },
                        "parent": [
                          "variables",
                          "data"
                        ],
                        "hint": "Defaults to nil if not supplied.",
                        "sticky": true
                      }
                    ],
                    "label": "Data",
                    "type": "object",
                    "name": "data"
                  }
                ],
                "type": "object"
              }
            ],
            "visible_config_fields": [
              "variables.data.public_key",
              "variables",
              "variables.schema",
              "variables.data.jwt_token",
              "variables.data",
              "variables.data.On_behalf_of_user_email",
              "variables.data.tete"
            ],
            "uuid": "07c4617e-2fb1-4a70-af91-4214ca87e9d2"
          },
          {
            "number": 4,
            "keyword": "try",
            "input": {
            },
            "block": [
              {
                "number": 5,
                "provider": "workato_variable",
                "name": "declare_variable",
                "as": "dfdb0f92",
                "keyword": "action",
                "input": {
                  "variables": {
                    "schema": "[{\"control_type\":\"text\",\"label\":\"decode_jwt\",\"name\":\"output\",\"type\":\"string\",\"optional\":true,\"details\":{\"real_name\":\"output\"},\"parent\":[\"variables\",\"data\"],\"hint\":\"Defaults to nil if not supplied.\",\"sticky\":true}]",
                    "data": {
                      "output": "=workato.jwt_decode(_dp('{\"pill_type\":\"output\",\"provider\":\"workato_api_platform\",\"line\":\"c2630a95\",\"path\":[\"context\",\"headers\",\"user_token\"]}'),_dp('{\"pill_type\":\"output\",\"provider\":\"workato_variable\",\"line\":\"e34d7184\",\"path\":[\"public_key\"]}'),\"RS256\")"
                    }
                  }
                },
                "extended_output_schema": [
                  {
                    "control_type": "text",
                    "hint": "Defaults to nil if not supplied.",
                    "label": "decode_jwt",
                    "name": "output",
                    "optional": true,
                    "sticky": true,
                    "type": "string",
                    "details": {
                      "real_name": "output"
                    }
                  }
                ],
                "extended_input_schema": [
                  {
                    "add_field_label": "Add a variable",
                    "control_type": "form-schema-builder",
                    "empty_schema_title": "Add variables by giving them a name, type and default value",
                    "exclude_fields": [
                      "hint"
                    ],
                    "item_label": "variable",
                    "label": "Variables",
                    "mark_as_required": true,
                    "name": "variables",
                    "ngIf": "!input.name",
                    "optional": true,
                    "properties": [
                      {
                        "control_type": "text",
                        "label": "Schema",
                        "extends_schema": true,
                        "broadcast_change_event": true,
                        "type": "string",
                        "name": "schema"
                      },
                      {
                        "properties": [
                          {
                            "control_type": "text",
                            "label": "decode_jwt",
                            "name": "output",
                            "type": "string",
                            "optional": true,
                            "details": {
                              "real_name": "output"
                            },
                            "parent": [
                              "variables",
                              "data"
                            ],
                            "hint": "Defaults to nil if not supplied.",
                            "sticky": true
                          }
                        ],
                        "label": "Data",
                        "type": "object",
                        "name": "data"
                      }
                    ],
                    "type": "object"
                  }
                ],
                "visible_config_fields": [
                  "variables.data.output"
                ],
                "uuid": "69c9144c-ab85-46b1-ac10-972539b4c345"
              },
              {
                "number": 6,
                "as": "18cb2bc3",
                "keyword": "catch",
                "input": {
                  "max_retry_count": "0",
                  "retry_interval": "2"
                },
                "block": [
                  {
                    "number": 7,
                    "provider": "workato_api_platform",
                    "name": "return_response",
                    "as": "b364ca51",
                    "keyword": "action",
                    "input": {
                      "http_status_code": "200",
                      "response": {
                        "output": "#{_dp('{\"pill_type\":\"output\",\"provider\":\"catch\",\"line\":\"18cb2bc3\",\"path\":[\"message\"]}')}"
                      }
                    },
                    "extended_output_schema": [
                      {
                        "change_on_blur": true,
                        "control_type": "select",
                        "extends_schema": true,
                        "label": "Response",
                        "name": "http_status_code",
                        "pick_list": [
                          [
                            "ok",
                            "200"
                          ]
                        ],
                        "type": "string"
                      },
                      {
                        "label": "Response body",
                        "name": "response",
                        "properties": [
                          {
                            "control_type": "text",
                            "label": "Output",
                            "type": "string",
                            "name": "output"
                          }
                        ],
                        "type": "object"
                      }
                    ],
                    "extended_input_schema": [
                      {
                        "change_on_blur": true,
                        "control_type": "select",
                        "extends_schema": true,
                        "label": "Response",
                        "name": "http_status_code",
                        "pick_list": [
                          [
                            "ok",
                            "200"
                          ]
                        ],
                        "type": "string"
                      },
                      {
                        "label": "Response body",
                        "name": "response",
                        "properties": [
                          {
                            "control_type": "text",
                            "label": "Output",
                            "type": "string",
                            "name": "output"
                          }
                        ],
                        "type": "object"
                      }
                    ],
                    "uuid": "b5c312b9-af4d-4471-bac8-1a6b05f68694",
                    "skip": false
                  }
                ],
                "uuid": "778f0f8d-9326-4b35-afca-e93e476f7849"
              }
            ],
            "uuid": "07e62391-00fb-4e8e-bd77-6cb789019d82"
          },
          {
            "number": 8,
            "provider": "workato_variable",
            "name": "update_variables",
            "as": "da78beac",
            "keyword": "action",
            "dynamicPickListSelection": {
              "name": [
                {
                  "label": "On_behalf_of_user_email (step 2)",
                  "value": "ded4dec7-b95c-4f49-b3c3-5b7f10004ed1:e232ff3e:output"
                }
              ]
            },
            "input": {
              "input_mode": "structured",
              "name": "ded4dec7-b95c-4f49-b3c3-5b7f10004ed1:e232ff3e:output",
              "output": "=_dp('{\"pill_type\":\"output\",\"provider\":\"workato_variable\",\"line\":\"dfdb0f92\",\"path\":[\"output\"]}')[\"payload\"][\"preferred_username\"]+\"@redhat.com.crm.sit\""
            },
            "extended_input_schema": [
              {
                "control_type": "text",
                "hint": "Provide a value for the variable. When the value is not supplied, the variable is not updated.<br>To clear the value, set the value to <b>nil</b> in formula mode.",
                "label": "On_behalf_of_user_email",
                "name": "output",
                "optional": true,
                "sticky": true,
                "type": "string",
                "strip_interpolation": true
              }
            ],
            "uuid": "8c99000a-df59-444f-820c-12f86dfb71f2"
          },
          {
            "number": 9,
            "keyword": "else",
            "input": {
            },
            "block": [
              {
                "number": 10,
                "provider": "workato_variable",
                "name": "update_variables",
                "as": "f2dea331",
                "keyword": "action",
                "dynamicPickListSelection": {
                  "name": [
                    {
                      "label": "On_behalf_of_user_email (step 2)",
                      "value": "ded4dec7-b95c-4f49-b3c3-5b7f10004ed1:e232ff3e:output"
                    }
                  ]
                },
                "input": {
                  "input_mode": "structured",
                  "name": "ded4dec7-b95c-4f49-b3c3-5b7f10004ed1:e232ff3e:output",
                  "output": "#{_dp('{\"pill_type\":\"output\",\"provider\":\"workato_api_platform\",\"line\":\"c2630a95\",\"path\":[\"context\",\"headers\",\"user_token\"]}')}"
                },
                "extended_input_schema": [
                  {
                    "control_type": "text",
                    "hint": "Provide a value for the variable. When the value is not supplied, the variable is not updated.<br>To clear the value, set the value to <b>nil</b> in formula mode.",
                    "label": "On_behalf_of_user_email",
                    "name": "output",
                    "optional": true,
                    "sticky": true,
                    "type": "string",
                    "strip_interpolation": true
                  }
                ],
                "uuid": "34e2b7a1-ffbc-4c84-be95-534f91aa5fb4"
              }
            ],
            "uuid": "a0c0b336-3366-4a02-895d-8b3f5bda1e6d"
          }
        ],
        "uuid": "4f9d14f2-e8a6-4f3c-aeff-4309c17e3575"
      },
      {
        "number": 11,
        "keyword": "try",
        "input": {
        },
        "block": [
          {
            "number": 12,
            "provider": "salesforce",
            "name": "search_sobjects_soql",
            "as": "ca19df3c",
            "keyword": "action",
            "dynamicPickListSelection": {
              "sobject_name": "Opportunity",
              "field_list": [
                {
                  "label": "Name",
                  "value": "Name"
                },
                {
                  "label": "Stage",
                  "value": "StageName"
                },
                {
                  "label": "Amount",
                  "value": "Amount"
                },
                {
                  "label": "Close Date",
                  "value": "CloseDate"
                },
                {
                  "label": "Account ID",
                  "value": "AccountId"
                },
                {
                  "label": "Opportunity ID",
                  "value": "Id"
                }
              ]
            },
            "input": {
              "limit": "15",
              "sobject_name": "Opportunity",
              "query": "Name LIKE '%#{_dp('{\"pill_type\":\"output\",\"provider\":\"workato_api_platform\",\"line\":\"c2630a95\",\"path\":[\"context\",\"headers\",\"opportunity_name\"]}')}%'",
              "requester_email": "#{_dp('{\"pill_type\":\"output\",\"provider\":\"workato_variable\",\"line\":\"e232ff3e\",\"path\":[\"output\"]}')}",
              "field_list": "Name\nStageName\nAmount\nCloseDate\nAccountId\nId"
            },
            "extended_output_schema": [
              {
                "label": "Opportunities",
                "name": "Opportunity",
                "of": "object",
                "properties": [
                  {
                    "control_type": "text",
                    "label": "Account ID",
                    "optional": true,
                    "custom": false,
                    "sfdc_createable": true,
                    "sfdc_updateable": true,
                    "type": "string",
                    "name": "AccountId"
                  },
                  {
                    "control_type": "number",
                    "label": "Amount",
                    "parse_output": "float_conversion",
                    "optional": true,
                    "custom": false,
                    "sfdc_createable": true,
                    "sfdc_updateable": true,
                    "type": "number",
                    "name": "Amount"
                  },
                  {
                    "control_type": "date",
                    "label": "Close Date",
                    "render_input": "render_iso8601_date",
                    "parse_output": "parse_iso8601_date",
                    "custom": false,
                    "sfdc_createable": true,
                    "sfdc_updateable": true,
                    "type": "date_time",
                    "name": "CloseDate"
                  },
                  {
                    "control_type": "text",
                    "label": "Name",
                    "event_title": true,
                    "custom": false,
                    "sfdc_createable": true,
                    "sfdc_updateable": true,
                    "type": "string",
                    "name": "Name"
                  },
                  {
                    "control_type": "text",
                    "label": "Opportunity ID",
                    "optional": true,
                    "custom": false,
                    "sfdc_createable": false,
                    "sfdc_updateable": false,
                    "type": "string",
                    "name": "Id"
                  },
                  {
                    "control_type": "select",
                    "label": "Stage",
                    "pick_list": "sobject_field_values_list",
                    "pick_list_params": {
                      "sobject_name": "\"Opportunity\"",
                      "field_name": "\"StageName\""
                    },
                    "toggle_hint": "Select from list",
                    "toggle_field": {
                      "control_type": "text",
                      "label": "Stage",
                      "toggle_hint": "Enter custom value",
                      "custom": false,
                      "sfdc_createable": true,
                      "sfdc_updateable": true,
                      "type": "string",
                      "name": "StageName"
                    },
                    "custom": false,
                    "sfdc_createable": true,
                    "sfdc_updateable": true,
                    "type": "string",
                    "name": "StageName"
                  },
                  {
                    "properties": [
                      {
                        "control_type": "number",
                        "label": "Total size",
                        "parse_output": "integer_conversion",
                        "type": "integer",
                        "name": "totalSize"
                      },
                      {
                        "label": "Files",
                        "of": "object",
                        "properties": [
                          {
                            "control_type": "text",
                            "label": "ID",
                            "type": "string",
                            "name": "Id"
                          },
                          {
                            "control_type": "number",
                            "label": "Content size",
                            "parse_output": "integer_conversion",
                            "type": "integer",
                            "name": "ContentSize"
                          },
                          {
                            "control_type": "url",
                            "label": "Content URL",
                            "type": "string",
                            "name": "ContentUrl"
                          },
                          {
                            "control_type": "text",
                            "label": "File extension",
                            "type": "string",
                            "name": "FileExtension"
                          },
                          {
                            "control_type": "text",
                            "label": "File type",
                            "type": "string",
                            "name": "FileType"
                          },
                          {
                            "control_type": "text",
                            "label": "Parent ID",
                            "type": "string",
                            "name": "ParentId"
                          },
                          {
                            "control_type": "text",
                            "label": "Record type",
                            "type": "string",
                            "name": "RecordType"
                          },
                          {
                            "control_type": "text",
                            "label": "Title",
                            "type": "string",
                            "name": "Title"
                          }
                        ],
                        "type": "array",
                        "name": "records"
                      }
                    ],
                    "label": "Combined attachments",
                    "sfdc_field_type": "CombinedAttachment",
                    "type": "object",
                    "name": "CombinedAttachments"
                  }
                ],
                "type": "array"
              },
              {
                "control_type": "number",
                "label": "List size",
                "name": "list_size",
                "parse_output": "integer_conversion",
                "type": "integer"
              },
              {
                "control_type": "checkbox",
                "label": "Processed all records?",
                "name": "done",
                "toggle_field": {
                  "label": "Processed all records?",
                  "control_type": "text",
                  "toggle_hint": "Use custom value",
                  "type": "boolean",
                  "render_input": null,
                  "parse_output": null,
                  "name": "done"
                },
                "toggle_hint": "Select from option list",
                "type": "boolean"
              },
              {
                "control_type": "integer",
                "label": "Total records",
                "name": "total_records",
                "parse_output": "integer_conversion",
                "type": "integer"
              },
              {
                "control_type": "url",
                "label": "Next page URL",
                "name": "next_page_url",
                "type": "string"
              }
            ],
            "extended_input_schema": [
              {
                "control_type": "checkbox",
                "disable_formula": true,
                "extends_schema": true,
                "hint": "Select <b>Yes</b> to obtain data from notes, attachments and files associated to the queried records. Default value is <b>Yes</b>.",
                "label": "Select combined attachments",
                "name": "include_combined_attachments",
                "optional": true,
                "support_pills": false,
                "type": "boolean"
              }
            ],
            "uuid": "65b7cba2-6e66-4951-8417-ae2dea9a1ff4"
          },
          {
            "number": 13,
            "as": "778baf3f",
            "keyword": "catch",
            "input": {
              "max_retry_count": "0",
              "retry_interval": "2"
            },
            "block": [
              {
                "number": 14,
                "provider": "workato_api_platform",
                "name": "return_response",
                "as": "17826700",
                "keyword": "action",
                "input": {
                  "http_status_code": "200",
                  "response": {
                    "output": "=_dp('{\"pill_type\":\"output\",\"provider\":\"catch\",\"line\":\"778baf3f\",\"path\":[\"message\"]}')"
                  }
                },
                "extended_output_schema": [
                  {
                    "change_on_blur": true,
                    "control_type": "select",
                    "extends_schema": true,
                    "label": "Response",
                    "name": "http_status_code",
                    "pick_list": [
                      [
                        "ok",
                        "200"
                      ]
                    ],
                    "type": "string"
                  },
                  {
                    "label": "Response body",
                    "name": "response",
                    "properties": [
                      {
                        "control_type": "text",
                        "label": "Output",
                        "type": "string",
                        "name": "output"
                      }
                    ],
                    "type": "object"
                  }
                ],
                "extended_input_schema": [
                  {
                    "change_on_blur": true,
                    "control_type": "select",
                    "extends_schema": true,
                    "label": "Response",
                    "name": "http_status_code",
                    "pick_list": [
                      [
                        "ok",
                        "200"
                      ]
                    ],
                    "type": "string"
                  },
                  {
                    "label": "Response body",
                    "name": "response",
                    "properties": [
                      {
                        "control_type": "text",
                        "label": "Output",
                        "type": "string",
                        "name": "output"
                      }
                    ],
                    "type": "object"
                  }
                ],
                "uuid": "4ac4fbb1-a190-43dd-bd42-48d735f77375",
                "skip": false
              }
            ],
            "uuid": "a0f26b89-ba02-4220-916c-d4c38ab496f8"
          }
        ],
        "uuid": "221e950f-7f8d-4881-a41b-172bb159268c"
      },
      {
        "number": 15,
        "provider": "workato_api_platform",
        "name": "return_response",
        "as": "b6bbdfcd",
        "keyword": "action",
        "input": {
          "http_status_code": "200",
          "response": {
            "output": "=_dp('{\"pill_type\":\"output\",\"provider\":\"salesforce\",\"line\":\"ca19df3c\",\"path\":[\"Opportunity\"]}')"
          }
        },
        "extended_output_schema": [
          {
            "change_on_blur": true,
            "control_type": "select",
            "extends_schema": true,
            "label": "Response",
            "name": "http_status_code",
            "pick_list": [
              [
                "ok",
                "200"
              ]
            ],
            "type": "string"
          },
          {
            "label": "Response body",
            "name": "response",
            "properties": [
              {
                "control_type": "text",
                "label": "Output",
                "type": "string",
                "name": "output"
              }
            ],
            "type": "object"
          }
        ],
        "extended_input_schema": [
          {
            "change_on_blur": true,
            "control_type": "select",
            "extends_schema": true,
            "label": "Response",
            "name": "http_status_code",
            "pick_list": [
              [
                "ok",
                "200"
              ]
            ],
            "type": "string"
          },
          {
            "label": "Response body",
            "name": "response",
            "properties": [
              {
                "control_type": "text",
                "label": "Output",
                "type": "string",
                "name": "output"
              }
            ],
            "type": "object"
          }
        ],
        "uuid": "de3cf84c-0a5d-41e5-a6a3-c2fa26e9726b",
        "skip": false
      }
    ],
    "comment": "Define the request and response parameters for this API endpoint",
    "uuid": "c42c51b3-37ba-4575-bb3b-f8e29462de08"
  },
  "config": [
    {
      "keyword": "application",
      "provider": "workato_api_platform",
      "skip_validation": false,
      "account_id": null
    },
    {
      "keyword": "application",
      "provider": "workato_variable",
      "skip_validation": false,
      "account_id": null
    },
    {
      "keyword": "application",
      "provider": "salesforce",
      "skip_validation": false,
      "account_id": {
        "zip_name": "Connections/sales_digital_service_account.connection.json",
        "name": "Sales Digital Service Account",
        "folder": "Connections"
      }
    }
  ]
}